test_pypi_nth_user/__init__.py
test_pypi_nth_user/main.py
test_pypi_nth_user-0.2.0.dist-info/METADATA
test_pypi_nth_user-0.2.0.dist-info/WHEEL
test_pypi_nth_user-0.2.0.dist-info/RECORD
