Metadata-Version: 2.3
Name: test-pypi-nth-user
Version: 0.2.0
Summary: this is a test to get nth user from an API
Author: 365ping
Author-email: abc@def.com
Requires-Python: >=3.9
Classifier: Programming Language :: Python :: 3
Classifier: Programming Language :: Python :: 3.9
Classifier: Programming Language :: Python :: 3.10
Classifier: Programming Language :: Python :: 3.11
Classifier: Programming Language :: Python :: 3.12
Classifier: Programming Language :: Python :: 3.13
Requires-Dist: requests (>=2.0,<3.0)
